ffeature/__init__.py
ffeature/features.py
ffeature/test.py
ffeature-0.0.4.dist-info/METADATA
ffeature-0.0.4.dist-info/WHEEL
ffeature-0.0.4.dist-info/top_level.txt
ffeature-0.0.4.dist-info/RECORD
